setup.py
distribution_of_probability/Binomialdistribution.py
distribution_of_probability/Gaussiandistribution.py
distribution_of_probability/Generaldistribution.py
distribution_of_probability/__init__.py
distribution_of_probability.egg-info/PKG-INFO
distribution_of_probability.egg-info/SOURCES.txt
distribution_of_probability.egg-info/dependency_links.txt
distribution_of_probability.egg-info/not-zip-safe
distribution_of_probability.egg-info/top_level.txt